{
  "crawledAt": "2025-11-28T01:57:28.403Z",
  "totalSources": 70,
  "totalArticles": 1,
  "aiFilterUsed": true,
  "articles": [
    {
      "title": "How to Apply Powerful AI Audio Models to Real-World Applications",
      "url": "https://pub.towardsai.net/how-to-apply-powerful-ai-audio-models-to-real-world-applications-fb7e0ebbb90e?source=rss----98111c9905da---4",
      "source": "Towards AI",
      "source_domain": "pub.towardsai.net",
      "source_category": "medium",
      "source_priority": "high",
      "pubDate": "2025-11-27T22:02:29.000Z",
      "metaDescription": "Learn about different types of AI audio models and the application areas they can be used in.\nContinue reading on Towards AI »",
      "category": "ai-agents",
      "difficulty": 5,
      "confidence": 0.2656508237935564,
      "crawledAt": "2025-11-28T01:56:27.073Z",
      "id": "3z5io0",
      "entities": [
        {
          "entity": "I-MISC",
          "score": 0.9472004771232605,
          "index": 14,
          "word": "World",
          "start": null,
          "end": null
        },
        {
          "entity": "I-MISC",
          "score": 0.9364861845970154,
          "index": 15,
          "word": "Applications",
          "start": null,
          "end": null
        }
      ],
      "summary": "Learn about different types of AI models and how they can be used in the future. Learn about different kinds of AI and how to use them.",
      "language": "en",
      "processed_at": "2025-11-28T01:57:39.315Z"
    }
  ],
  "processedAt": "2025-11-28T01:57:39.324Z",
  "categories": [
    "ai-agents"
  ],
  "processingMethod": "ai-powered",
  "newArticlesProcessed": 1,
  "dailyArticlesCount": 1,
  "filterDate": "2025-11-28"
}